vaganboost/__init__.py
vaganboost/data_utils.py
vaganboost/models.py
vaganboost/train.py
vaganboost/utils.py
vaganboost-0.7.7.dist-info/LICENSE
vaganboost-0.7.7.dist-info/METADATA
vaganboost-0.7.7.dist-info/WHEEL
vaganboost-0.7.7.dist-info/entry_points.txt
vaganboost-0.7.7.dist-info/top_level.txt
vaganboost-0.7.7.dist-info/RECORD
