Metadata-Version: 2.1
Name: vaganboost
Version: 0.7.7
Summary: A hybrid model combining VAE, GAN, and LightGBM for boosting performance in high-energy physics or data analysis tasks.
Home-page: https://github.com/AliBavarchee/vaganboost
Author: Ali Bavarchee
Author-email: ali.bavarchee@gmail.com
Classifier: Programming Language :: Python :: 3
Classifier: Programming Language :: Python :: 3.6
Classifier: Programming Language :: Python :: 3.7
Classifier: Programming Language :: Python :: 3.8
Classifier: Programming Language :: Python :: 3.9
Classifier: Programming Language :: Python :: 3.10
Classifier: License :: OSI Approved :: MIT License
Classifier: Operating System :: OS Independent
Requires-Python: >=3.6
License-File: LICENSE
Requires-Dist: torch >=1.8.0
Requires-Dist: lightgbm >=3.2.0
Requires-Dist: numpy >=1.19.0
Requires-Dist: pandas >=1.1.0
Requires-Dist: scikit-learn >=0.24.0
Requires-Dist: matplotlib >=3.3.0
Requires-Dist: seaborn >=0.11.0
Requires-Dist: plotly >=5.0.0
Provides-Extra: dev
Requires-Dist: pytest >=6.0 ; extra == 'dev'
Requires-Dist: sphinx >=4.0 ; extra == 'dev'
Requires-Dist: black ; extra == 'dev'
